odoo8_addon_connector_salesforce_server_environment-8.0.1.0.0-py2.7-nspkg.pth
odoo_addons/connector_salesforce_server_environment/__openerp__.py
odoo_addons/connector_salesforce_server_environment/backend_model.py
odoo_addons/connector_salesforce_server_environment/__init__.py
odoo8_addon_connector_salesforce_server_environment-8.0.1.0.0.dist-info/top_level.txt
odoo8_addon_connector_salesforce_server_environment-8.0.1.0.0.dist-info/WHEEL
odoo8_addon_connector_salesforce_server_environment-8.0.1.0.0.dist-info/RECORD
odoo8_addon_connector_salesforce_server_environment-8.0.1.0.0.dist-info/metadata.json
odoo8_addon_connector_salesforce_server_environment-8.0.1.0.0.dist-info/DESCRIPTION.rst
odoo8_addon_connector_salesforce_server_environment-8.0.1.0.0.dist-info/METADATA
odoo8_addon_connector_salesforce_server_environment-8.0.1.0.0.dist-info/namespace_packages.txt
