Metadata-Version: 2.0
Name: odoo8-addon-connector-salesforce-server-environment
Version: 8.0.1.0.0
Summary: Connector Salesforce Server Environment
Home-page: http://www.camptocamp.com
Author: Camptocamp, Odoo Community Association (OCA)
Author-email: support@odoo-community.org
License: AGPL-3
Platform: UNKNOWN
Requires-Dist: odoo (<9.0a,>=8.0a)
Requires-Dist: odoo8-addon-connector-salesforce
Requires-Dist: odoo8-addon-server-environment
Classifier: Programming Language :: Python :: 2.7
Classifier: Framework :: Odoo
Classifier: License :: OSI Approved :: GNU Affero General Public License v3
